{
  "source": "Distrupol (https://www.distrupol.com/polymer_abbreviations.html), PolySource",
  "abbreviations": {
    "ABS": "acrylonitrile butadiene styrene",
    "ASA": "acrylonitrile styrene acrylate",
    "BR": "butadiene rubber",
    "CA": "cellulose acetate",
    "CAB": "cellulose acetate butyrate",
    "COC": "cycloolefin copolymer",
    "CPE": "chlorinated polyethylene",
    "CPVC": "chlorinated polyvinyl chloride",
    "EBA": "ethylene butyl acetate",
    "EPDM": "ethylene propylene diene monomer",
    "EPS": "expandable polystyrene",
    "ESBR": "emulsion styrene butadiene rubber",
    "EVA": "ethylene vinyl acetate",
    "EVOH": "ethylene vinyl alcohol",
    "FEP": "fluorinated ethylene propylene",
    "GPPS": "general purpose polystyrene",
    "HDPE": "high density polyethylene",
    "HIPS": "high impact polystyrene",
    "LCP": "liquid crystal polymer",
    "LDPE": "low density polyethylene",
    "LLDPE": "linear low density polyethylene",
    "MABS": "methyl methacrylate acrylonitrile butadiene styrene",
    "MDPE": "medium density polyethylene",
    "NBR": "nitrile butadiene rubber",
    "PA": "polyamide",
    "PA6": "polyamide 6",
    "PA66": "polyamide 66",
    "PA 6": "polyamide 6",
    "PA 66": "polyamide 66",
    "PA 11": "polyamide 11",
    "PA 12": "polyamide 12",
    "PBT": "polybutylene terephthalate",
    "PC": "polycarbonate",
    "PCL": "polycaprolactone",
    "PE": "polyethylene",
    "PEEK": "polyetheretherketone",
    "PEI": "polyetherimide",
    "PES": "polyether sulfone",
    "PET": "polyethylene terephthalate",
    "PMMA": "polymethyl methacrylate",
    "POM": "polyoxymethylene",
    "PP": "polypropylene",
    "PPA": "polyphthalamide",
    "PPE": "polyphenylene ether",
    "PPS": "polyphenylene sulfide",
    "PPSU": "polyphenylene sulfone",
    "PS": "polystyrene",
    "PTFE": "polytetrafluoroethylene",
    "PU": "polyurethane",
    "PUR": "polyurethane",
    "PVA": "polyvinyl alcohol",
    "PVAC": "polyvinyl acetate",
    "PVC": "polyvinyl chloride",
    "PVDC": "polyvinylidene chloride",
    "PVDF": "polyvinylidene fluoride",
    "PVP": "polyvinyl pyrrolidone",
    "SAN": "styrene acrylonitrile",
    "SBC": "styrene butadiene copolymer",
    "SBS": "styrene butadiene styrene block copolymer",
    "SEBS": "styrene ethylene butylene styrene block copolymer",
    "TPE": "thermoplastic elastomer",
    "TPU": "thermoplastic polyurethane",
    "TPV": "thermoplastic vulcanizate",
    "UHMWPE": "ultra high molecular weight polyethylene",
    "ULDPE": "ultra low density polyethylene",
    "VLDPE": "very low density polyethylene",
    "XLPE": "crosslinked polyethylene",
    "PLA": "polylactic acid",
    "PEG": "polyethylene glycol",
    "PEO": "polyethylene oxide",
    "PVP": "polyvinylpyrrolidone",
    "PBLG": "poly(γ-benzyl-L-glutamate)",
    "GelMA": "gelatin methacrylate",
    "PETG": "polyethylene terephthalate glycol-modified",
    "APE": "aromatic polyesters",
  }
}
